<?xml version="1.0" encoding="UTF-8"?>
<beans xmlns="http://www.springframework.org/schema/beans"
   xmlns:context="http://www.springframework.org/schema/context"
   xmlns:xsi="http://www.w3.org/2001/XMLSchema-instance"
   xsi:schemaLocation="http://www.springframework.org/schema/beans
   http://www.springframework.org/schema/beans/spring-beans.xsd
   http://www.springframework.org/schema/context
   http://www.springframework.org/schema/context/spring-context.xsd">
   <context:annotation-config />
   <bean id="temp1" class="com.springcore.autowire.annotation.Address">
      <property name="street" value="Temp Street"/>
      <property name="city" value="Temp city"/>
   </bean>
   <!-- namee or id is not important for autowired -->
   <bean id="temp2" class="com.springcore.autowire.annotation.Address">
      <property name="street" value="Temp Delhi"/>
      <property name="city" value="Temp Mumbai"/>
   </bean>
<!-- at this stage autowire gert confuse use Qualifies -->
   
    <bean id="emp1" class="com.springcore.autowire.annotation.Emp1"> 
   </bean>

</beans>
